[
  {
    "label": "所有商品",
    "url": "http://localhost:3000/product/list"
  },
  {
    "label": "商品種類",
    "url": "",
    "children": [
      {
        "label": "帳篷",
        "url": "http://localhost:3000/product/list?cat_ids=1",
        "children": [
          {
            "label": "colman",
            "url": "http://localhost:3000/product/list?cat_ids=1&brand=1"
          },
          {
            "label": "snow peak",
            "url": "http://localhost:3000/product/list?cat_ids=1&brand=2"
          },
          {
            "label": "D.O.D",
            "url": "http://localhost:3000/product/list?cat_ids=1&brand=3"
          },
          {
            "label": "CAPTAIN STAG",
            "url": "http://localhost:3000/product/list?cat_ids=1&brand=4"
          },
          {
            "label": "LOGOS",
            "url": "http://localhost:3000/product/list?cat_ids=1&brand=5"
          }
        ]
      },
      {
        "label": "照明用具",
        "url": "http://localhost:3000/product/list?cat_ids=2",
        "children": [
          {
            "label": "colman",
            "url": "http://localhost:3000/product/list?cat_ids=2&brand=1"
          },
          {
            "label": "snow peak",
            "url": "http://localhost:3000/product/list?cat_ids=2&brand=2"
          },
          {
            "label": "D.O.D",
            "url": "http://localhost:3000/product/list?cat_ids=2&brand=3"
          },
          {
            "label": "CAPTAIN STAG",
            "url": "http://localhost:3000/product/list?cat_ids=2&brand=4"
          },
          {
            "label": "LOGOS",
            "url": "http://localhost:3000/product/list?cat_ids=2&brand=5"
          }
        ]
      },
      {
        "label": "貼身配件",
        "url": "http://localhost:3000/product/list?cat_ids=3",
        "children": [
          {
            "label": "colman",
            "url": "http://localhost:3000/product/list?cat_ids=3&brand=1"
          },
          {
            "label": "snow peak",
            "url": "http://localhost:3000/product/list?cat_ids=3&brand=2"
          },
          {
            "label": "D.O.D",
            "url": "http://localhost:3000/product/list?cat_ids=3&brand=3"
          },
          {
            "label": "CAPTAIN STAG",
            "url": "http://localhost:3000/product/list?cat_ids=3&brand=4"
          },
          {
            "label": "LOGOS",
            "url": "http://localhost:3000/product/list?cat_ids=3&brand=5"
          }
        ]
      },
      {
        "label": "野炊用具",
        "url": "http://localhost:3000/product/list?cat_ids=4",
        "children": [
          {
            "label": "colman",
            "url": "http://localhost:3000/product/list?cat_ids=4&brand=1"
          },
          {
            "label": "snow peak",
            "url": "http://localhost:3000/product/list?cat_ids=4&brand=2"
          },
          {
            "label": "D.O.D",
            "url": "http://localhost:3000/product/list?cat_ids=4&brand=3"
          },
          {
            "label": "CAPTAIN STAG",
            "url": "http://localhost:3000/product/list?cat_ids=4&brand=4"
          },
          {
            "label": "LOGOS",
            "url": "http://localhost:3000/product/list?cat_ids=4&brand=5"
          }
        ]
      },
      {
        "label": "其他工具",
        "url": "http://localhost:3000/product/list?cat_ids=5",
        "children": [
          {
            "label": "colman",
            "url": "http://localhost:3000/product/list?cat_ids=5&brand=1"
          },
          {
            "label": "snow peak",
            "url": "http://localhost:3000/product/list?cat_ids=5&brand=2"
          },
          {
            "label": "D.O.D",
            "url": "http://localhost:3000/product/list?cat_ids=5&brand=3"
          },
          {
            "label": "CAPTAIN STAG",
            "url": "http://localhost:3000/product/list?cat_ids=5&brand=4"
          },
          {
            "label": "LOGOS",
            "url": "http://localhost:3000/product/list?cat_ids=5&brand=5"
          }
        ]
      }
    ]
  },
  {
    "label": "品牌",
    "url": "",
    "children": [
      {
        "label": "colman",
        "url": "",
        "children": [
          {
            "label": "帳篷",
            "url": "http://localhost:3000/product/list?cat_ids=1&brand=1"
          },
          {
            "label": "照明用具",
            "url": "http://localhost:3000/product/list?cat_ids=2&brand=1"
          },
          {
            "label": "貼身配件",
            "url": "http://localhost:3000/product/list?cat_ids=3&brand=1"
          },
          {
            "label": "野炊用具",
            "url": "http://localhost:3000/product/list?cat_ids=4&brand=1"
          },
          {
            "label": "其他工具",
            "url": "http://localhost:3000/product/list?cat_ids=5&brand=1"
          }
        ]
      },
      {
        "label": "snow peak",
        "url": "",
        "children": [
          {
            "label": "帳篷",
            "url": "http://localhost:3000/product/list?cat_ids=1&brand=2"
          },
          {
            "label": "照明用具",
            "url": "http://localhost:3000/product/list?cat_ids=2&brand=2"
          },
          {
            "label": "貼身配件",
            "url": "http://localhost:3000/product/list?cat_ids=3&brand=2"
          },
          {
            "label": "野炊用具",
            "url": "http://localhost:3000/product/list?cat_ids=4&brand=2"
          },
          {
            "label": "其他工具",
            "url": "http://localhost:3000/product/list?cat_ids=5&brand=2"
          }
        ]
      },
      {
        "label": "D.O.D",
        "url": "",
        "children": [
          {
            "label": "帳篷",
            "url": "http://localhost:3000/product/list?cat_ids=1&brand=3"
          },
          {
            "label": "照明用具",
            "url": "http://localhost:3000/product/list?cat_ids=2&brand=3"
          },
          {
            "label": "貼身配件",
            "url": "http://localhost:3000/product/list?cat_ids=3&brand=3"
          },
          {
            "label": "野炊用具",
            "url": "http://localhost:3000/product/list?cat_ids=4&brand=3"
          },
          {
            "label": "其他工具",
            "url": "http://localhost:3000/product/list?cat_ids=5&brand=3"
          }
        ]
      },
      {
        "label": "CAPTAIN STAG",
        "url": "",
        "children": [
          {
            "label": "帳篷",
            "url": "http://localhost:3000/product/list?cat_ids=1&brand=4"
          },
          {
            "label": "照明用具",
            "url": "http://localhost:3000/product/list?cat_ids=2&brand=4"
          },
          {
            "label": "貼身配件",
            "url": "http://localhost:3000/product/list?cat_ids=3&brand=4"
          },
          {
            "label": "野炊用具",
            "url": "http://localhost:3000/product/list?cat_ids=4&brand=4"
          },
          {
            "label": "其他工具",
            "url": "http://localhost:3000/product/list?cat_ids=5&brand=4"
          }
        ]
      },
      {
        "label": "LOGOS",
        "url": "",
        "children": [
          {
            "label": "帳篷",
            "url": "http://localhost:3000/product/list?cat_ids=1&brand=5"
          },
          {
            "label": "照明用具",
            "url": "http://localhost:3000/product/list?cat_ids=2&brand=5"
          },
          {
            "label": "貼身配件",
            "url": "http://localhost:3000/product/list?cat_ids=3&brand=5"
          },
          {
            "label": "野炊用具",
            "url": "http://localhost:3000/product/list?cat_ids=4&brand=5"
          },
          {
            "label": "其他工具",
            "url": "http://localhost:3000/product/list?cat_ids=5&brand=5"
          }
        ]
      }
    ]
  }
]
